README.md
setup.py
prisma_get_info/__init__.py
prisma_get_info/default_data.py
prisma_get_info/versions.py
prisma_get_info.egg-info/PKG-INFO
prisma_get_info.egg-info/SOURCES.txt
prisma_get_info.egg-info/dependency_links.txt
prisma_get_info.egg-info/entry_points.txt
prisma_get_info.egg-info/requires.txt
prisma_get_info.egg-info/top_level.txt