Metadata-Version: 2.1
Name: prisma-get-info
Version: 1.0.1b1
Summary: Utility to interact with Prisma via Panorama.
Home-page: https://github.com/ebob9/prisma_get_info
Author: Aaron Edwards
Author-email: prisma_get_info@ebob9.com
License: MIT
Platform: UNKNOWN
Classifier: Development Status :: 5 - Production/Stable
Classifier: Intended Audience :: Developers
Classifier: License :: OSI Approved :: MIT License
Classifier: Programming Language :: Python :: 3.7
Classifier: Programming Language :: Python :: 3.8
Classifier: Programming Language :: Python :: 3.9
